linkedmcp/__init__.py
linkedmcp/helper.py
linkedmcp/prompts.py
linkedmcp/server.py
linkedmcp-0.2.0.dist-info/licenses/LICENSE
linkedmcp-0.2.0.dist-info/METADATA
linkedmcp-0.2.0.dist-info/WHEEL
linkedmcp-0.2.0.dist-info/entry_points.txt
linkedmcp-0.2.0.dist-info/top_level.txt
linkedmcp-0.2.0.dist-info/RECORD
